waiter/__init__.py
waiter/api_navigator.py
waiter/dataclasses.py
waiter/exceptions.py
waiter/helpers.py
waiter/waiter.py
eAwaiter-0.0.3.dist-info/LICENSE
eAwaiter-0.0.3.dist-info/METADATA
eAwaiter-0.0.3.dist-info/WHEEL
eAwaiter-0.0.3.dist-info/top_level.txt
eAwaiter-0.0.3.dist-info/RECORD
