Metadata-Version: 2.1
Name: eAwaiter
Version: 0.0.3
Summary: Package to manage your eAsistent meals automatically.
Home-page: https://github.com/5KRC1/eAwaiter
Author: 5krc1
Author-email: skrci@dasadweb.com
License: MIT
Classifier: Programming Language :: Python :: 3
Classifier: License :: OSI Approved :: MIT License
Classifier: Operating System :: OS Independent
Requires-Python: >=3.9
License-File: LICENSE
Requires-Dist: beautifulsoup4 (>=4.12.0)
Requires-Dist: requests (>=2.28.2)
